pnu_rot13-1.0.6.data/data/man/man3/rot13.3.gz
pnu_rot13-1.0.6.data/data/man/man6/rot13.6.gz
rot13/__init__.py
rot13/main.py
pnu_rot13-1.0.6.dist-info/License
pnu_rot13-1.0.6.dist-info/METADATA
pnu_rot13-1.0.6.dist-info/WHEEL
pnu_rot13-1.0.6.dist-info/entry_points.txt
pnu_rot13-1.0.6.dist-info/top_level.txt
pnu_rot13-1.0.6.dist-info/RECORD
